africanus/__init__.py
africanus/conftest.py
africanus/averaging/__init__.py
africanus/averaging/bda_avg.py
africanus/averaging/bda_mapping.py
africanus/averaging/dask.py
africanus/averaging/shared.py
africanus/averaging/splines.py
africanus/averaging/support.py
africanus/averaging/time_and_channel_avg.py
africanus/averaging/time_and_channel_mapping.py
africanus/averaging/tests/__init__.py
africanus/averaging/tests/test_bda_averaging.py
africanus/averaging/tests/test_bda_mapping.py
africanus/averaging/tests/test_mapping.py
africanus/averaging/tests/test_splines.py
africanus/averaging/tests/test_support.py
africanus/averaging/tests/test_time_and_channel_averaging.py
africanus/calibration/__init__.py
africanus/calibration/phase_only/__init__.py
africanus/calibration/phase_only/dask.py
africanus/calibration/phase_only/phase_only.py
africanus/calibration/phase_only/tests/__init__.py
africanus/calibration/phase_only/tests/conftest.py
africanus/calibration/phase_only/tests/test_phase_only.py
africanus/calibration/tests/__init__.py
africanus/calibration/tests/conftest.py
africanus/calibration/utils/__init__.py
africanus/calibration/utils/compute_and_corrupt_vis.py
africanus/calibration/utils/correct_vis.py
africanus/calibration/utils/corrupt_vis.py
africanus/calibration/utils/dask.py
africanus/calibration/utils/residual_vis.py
africanus/calibration/utils/utils.py
africanus/calibration/utils/examples/apply_gains_time_varying_sources.py
africanus/calibration/utils/examples/apply_gains_to_ms.py
africanus/calibration/utils/examples/apply_phase_screen_to_ms.py
africanus/calibration/utils/tests/__init__.py
africanus/calibration/utils/tests/conftest.py
africanus/calibration/utils/tests/test_utils.py
africanus/constants/__init__.py
africanus/constants/consts.py
africanus/coordinates/__init__.py
africanus/coordinates/coordinates.py
africanus/coordinates/dask.py
africanus/coordinates/tests/test_coordinates.py
africanus/deconv/__init__.py
africanus/deconv/hogbom/__init__.py
codex_africanus-0.4.3.dist-info/METADATA
codex_africanus-0.4.3.dist-info/WHEEL
codex_africanus-0.4.3.dist-info/licenses/AUTHORS.rst
codex_africanus-0.4.3.dist-info/licenses/LICENSE
codex_africanus-0.4.3.dist-info/RECORD
