Metadata-Version: 2.4
Name: codex-africanus
Version: 0.4.3
Summary: Radio Astronomy Building Blocks
Author-email: Simon Perkins <simon.perkins@gmail.com>
License-File: AUTHORS.rst
License-File: LICENSE
Requires-Python: <4.0,>=3.10
Requires-Dist: appdirs>=1.4.4
Requires-Dist: decorator>=5.1.1
Requires-Dist: numba>=0.60
Requires-Dist: numpy>=2.0
Provides-Extra: astropy
Requires-Dist: astropy>=6.1.4; extra == 'astropy'
Provides-Extra: complete
Requires-Dist: astropy; extra == 'complete'
Requires-Dist: dask; extra == 'complete'
Requires-Dist: ducc0; extra == 'complete'
Requires-Dist: jax; extra == 'complete'
Requires-Dist: jaxlib; extra == 'complete'
Requires-Dist: python-casacore; extra == 'complete'
Requires-Dist: scipy; extra == 'complete'
Provides-Extra: complete-cuda
Requires-Dist: astropy; extra == 'complete-cuda'
Requires-Dist: cupy; extra == 'complete-cuda'
Requires-Dist: dask; extra == 'complete-cuda'
Requires-Dist: ducc0; extra == 'complete-cuda'
Requires-Dist: jax; extra == 'complete-cuda'
Requires-Dist: jaxlib; extra == 'complete-cuda'
Requires-Dist: jinja2; extra == 'complete-cuda'
Requires-Dist: python-casacore; extra == 'complete-cuda'
Requires-Dist: scipy; extra == 'complete-cuda'
Provides-Extra: cuda
Requires-Dist: cupy>=13.3.0; extra == 'cuda'
Requires-Dist: jinja2>=3.1.4; extra == 'cuda'
Provides-Extra: dask
Requires-Dist: dask[array]>=2024.0; extra == 'dask'
Provides-Extra: dev
Requires-Dist: pre-commit>=4.3.0; extra == 'dev'
Requires-Dist: ruff>=0.14.0; extra == 'dev'
Requires-Dist: tbump>=6.11.0; extra == 'dev'
Provides-Extra: doc
Requires-Dist: numpydoc>=1.9.0; extra == 'doc'
Requires-Dist: pydata-sphinx-theme>=0.16.1; extra == 'doc'
Requires-Dist: pygments>=2.19.2; extra == 'doc'
Requires-Dist: ruff>=0.14.0; extra == 'doc'
Requires-Dist: sphinx-copybutton>=0.5.2; extra == 'doc'
Requires-Dist: sphinx>=8.1.3; extra == 'doc'
Provides-Extra: ducc0
Requires-Dist: ducc0>=0.35.0; extra == 'ducc0'
Provides-Extra: jax
Requires-Dist: jax>=0.4.35; extra == 'jax'
Requires-Dist: jaxlib>=0.4.35; extra == 'jax'
Provides-Extra: python-casacore
Requires-Dist: python-casacore>=3.6.1; extra == 'python-casacore'
Provides-Extra: scipy
Requires-Dist: scipy>=1.14.1; extra == 'scipy'
Provides-Extra: testing
Requires-Dist: flaky>=3.8.1; extra == 'testing'
Requires-Dist: pytest>=8.0.0; extra == 'testing'
